vellox/__init__.py
vellox/adapter.py
vellox/exceptions.py
vellox/handlers/__init__.py
vellox/handlers/gcp.py
vellox/handlers/utils.py
vellox/protocols/__init__.py
vellox/protocols/http.py
vellox/protocols/lifespan.py
vellox/py.typed
vellox/types.py
vellox-0.1.3.dist-info/LICENSE
vellox-0.1.3.dist-info/METADATA
vellox-0.1.3.dist-info/WHEEL
vellox-0.1.3.dist-info/RECORD
