Metadata-Version: 2.1
Name: vellox
Version: 0.1.3
Summary: GCP Cloud Functions support for ASGI applications
Home-page: https://vellox.junah.dev
License: MIT
Author: junah201
Author-email: junah.dev@gmail.com
Requires-Python: >=3.8
Classifier: License :: OSI Approved :: MIT License
Classifier: Operating System :: OS Independent
Classifier: Programming Language :: Python
Classifier: Programming Language :: Python :: 3
Classifier: Programming Language :: Python :: 3.8
Classifier: Programming Language :: Python :: 3.9
Classifier: Programming Language :: Python :: 3.10
Classifier: Programming Language :: Python :: 3.11
Classifier: Programming Language :: Python :: 3.12
Requires-Dist: Flask (==2.2.5)
Requires-Dist: typing_extensions (>=4.7.1,<5)
Project-URL: Documentation, https://vellox.junah.dev
Project-URL: Repository, https://github.com/junah201/vellox
